jibix/__init__.py
jibix/jibix.py
jibix-0.4.dist-info/METADATA
jibix-0.4.dist-info/WHEEL
jibix-0.4.dist-info/top_level.txt
jibix-0.4.dist-info/RECORD
