Metadata-Version: 2.1
Name: jibix
Version: 0.4
Summary: Easy to handle json database manager
Author: Dr3xxine
Author-email: dr3xxine@gmail.com
Classifier: Programming Language :: Python :: 3
Classifier: Operating System :: OS Independent
Requires-Python: >=3.6
